{
  "Top": "matrixmul",
  "RtlTop": "matrixmul",
  "RtlPrefix": "",
  "RtlSubPrefix": "matrixmul_",
  "SourceLanguage": "cpp",
  "HostMachineBits": "64",
  "FunctionProtocol": "ap_ctrl_hs",
  "ResetStyle": "control",
  "Target": {
    "Family": "spartan7",
    "Device": "xc7s75",
    "Package": "-fgga676",
    "Speed": "-1",
    "Triple": "fpga64-xilinx-none"
  },
  "Args": {
    "a": {
      "index": "0",
      "direction": "in",
      "srcType": "unsigned char*",
      "srcSize": "8",
      "hwRefs": [{
          "type": "port",
          "interface": "a",
          "name": "a",
          "usage": "data",
          "direction": "in"
        }]
    },
    "b": {
      "index": "1",
      "direction": "in",
      "srcType": "unsigned char*",
      "srcSize": "8",
      "hwRefs": [{
          "type": "port",
          "interface": "b",
          "name": "b",
          "usage": "data",
          "direction": "in"
        }]
    },
    "res": {
      "index": "2",
      "direction": "out",
      "srcType": "unsigned short*",
      "srcSize": "16",
      "hwRefs": [
        {
          "type": "port",
          "interface": "res",
          "name": "res",
          "usage": "data",
          "direction": "out"
        },
        {
          "type": "port",
          "interface": "res_ap_vld",
          "name": "res_ap_vld",
          "usage": "control",
          "direction": "out"
        }
      ]
    }
  },
  "HlsSolution": {
    "FlowTarget": "vivado",
    "DirectiveTcl": [
      "set_directive_top matrixmul -name matrixmul",
      "set_directive_unroll matrixmul\/Product",
      "set_directive_unroll matrixmul\/Col",
      "set_directive_unroll matrixmul\/Row",
      "set_directive_array_reshape matrixmul -type complete -dim 0 a",
      "set_directive_array_reshape matrixmul -type complete -dim 0 b",
      "set_directive_array_reshape matrixmul -type complete -dim 0 res",
      "set_directive_top matrixmul -name matrixmul"
    ],
    "ProfileOption": "0",
    "ProfileType": "none",
    "KernelName": "matrixmul"
  },
  "ClockInfo": {
    "ClockName": "ap_clk",
    "ClockPeriod": "5",
    "Uncertainty": "1.35",
    "IsCombinational": "0",
    "II": "5",
    "Latency": "4"
  },
  "Xdc": {"OocClocks": ["create_clock -name ap_clk -period 5.000 [get_ports ap_clk]"]},
  "Ipx": {
    "Vendor": "xilinx.com",
    "Library": "hls",
    "Name": "matrixmul",
    "Version": "1.0",
    "DisplayName": "Matrixmul",
    "Revision": "2113681065",
    "Description": "An IP generated by Vitis HLS",
    "Taxonomy": "\/VITIS_HLS_IP",
    "AutoFamilySupport": "",
    "ZipFile": "xilinx_com_hls_matrixmul_1_0.zip"
  },
  "Files": {
    "CSource": ["..\/..\/HLS_files\/matrixmul.cpp"],
    "Vhdl": [
      "impl\/vhdl\/matrixmul_mac_muladd_8ns_8ns_16ns_16_4_1.vhd",
      "impl\/vhdl\/matrixmul_mul_8ns_8ns_16_3_1.vhd",
      "impl\/vhdl\/matrixmul.vhd"
    ],
    "Verilog": [
      "impl\/verilog\/matrixmul_mac_muladd_8ns_8ns_16ns_16_4_1.v",
      "impl\/verilog\/matrixmul_mul_8ns_8ns_16_3_1.v",
      "impl\/verilog\/matrixmul.v"
    ],
    "IpMisc": ["impl\/misc\/logo.png"],
    "CsynthXml": "syn\/report\/csynth.xml",
    "DebugDir": ".debug",
    "KernelXml": ".autopilot\/db\/kernel.internal.xml",
    "Xo": "",
    "XoHlsDir": "",
    "ProtoInst": [".debug\/matrixmul.protoinst"]
  },
  "SubcoreInfo": {
    "HasXpmMemory": false,
    "HasClockedDsp": false,
    "Ip": []
  },
  "Interfaces": {
    "ap_clk": {
      "type": "clock",
      "busTypeName": "clock",
      "mode": "slave",
      "busParams": {"ASSOCIATED_RESET": "ap_rst"},
      "portMap": {"ap_clk": "CLK"},
      "ports": ["ap_clk"]
    },
    "ap_rst": {
      "type": "reset",
      "busTypeName": "reset",
      "mode": "slave",
      "busParams": {"POLARITY": "ACTIVE_HIGH"},
      "portMap": {"ap_rst": "RST"},
      "ports": ["ap_rst"]
    },
    "ap_ctrl": {
      "type": "ap_ctrl",
      "busTypeName": "acc_handshake",
      "mode": "slave",
      "portMap": {
        "ap_start": "start",
        "ap_done": "done",
        "ap_idle": "idle",
        "ap_ready": "ready"
      },
      "ports": [
        "ap_done",
        "ap_idle",
        "ap_ready",
        "ap_start"
      ]
    },
    "a": {
      "type": "data",
      "busTypeName": "data",
      "protocol": "ap_none",
      "mode": "slave",
      "dataWidth": "32",
      "portMap": {"a": "DATA"},
      "ports": ["a"],
      "constraints": [{
          "constraint_type": "pragma interface",
          "mode": "ap_none",
          "register_option": "0",
          "argName": "a"
        }]
    },
    "b": {
      "type": "data",
      "busTypeName": "data",
      "protocol": "ap_none",
      "mode": "slave",
      "dataWidth": "32",
      "portMap": {"b": "DATA"},
      "ports": ["b"],
      "constraints": [{
          "constraint_type": "pragma interface",
          "mode": "ap_none",
          "register_option": "0",
          "argName": "b"
        }]
    },
    "res": {
      "type": "data",
      "busTypeName": "data",
      "protocol": "ap_vld",
      "mode": "master",
      "dataWidth": "64",
      "portMap": {"res": "DATA"},
      "ports": ["res"],
      "constraints": [{
          "constraint_type": "pragma interface",
          "mode": "ap_none",
          "register_option": "0",
          "argName": "res"
        }]
    }
  },
  "RtlPorts": {
    "ap_clk": {
      "dir": "in",
      "width": "1"
    },
    "ap_rst": {
      "dir": "in",
      "width": "1"
    },
    "ap_start": {
      "dir": "in",
      "width": "1"
    },
    "ap_done": {
      "dir": "out",
      "width": "1"
    },
    "ap_idle": {
      "dir": "out",
      "width": "1"
    },
    "ap_ready": {
      "dir": "out",
      "width": "1"
    },
    "a": {
      "dir": "in",
      "width": "32"
    },
    "b": {
      "dir": "in",
      "width": "32"
    },
    "res": {
      "dir": "out",
      "width": "64"
    },
    "res_ap_vld": {
      "dir": "out",
      "width": "1"
    }
  },
  "ModuleInfo": {
    "Hierarchy": {"ModuleName": "matrixmul"},
    "Info": {"matrixmul": {
        "FunctionProtocol": "ap_ctrl_hs",
        "isTaskLevelControl": "0",
        "isPipelined": "0",
        "isCombinational": "0",
        "isOneStateSeq": "0"
      }},
    "Metrics": {"matrixmul": {
        "Latency": {
          "LatencyBest": "4",
          "LatencyAvg": "4",
          "LatencyWorst": "4",
          "PipelineII": "5",
          "PipelineDepth": "",
          "PipelineType": "no"
        },
        "Timing": {
          "Target": "5.00",
          "Uncertainty": "1.35",
          "Estimate": "2.932"
        },
        "Area": {
          "DSP": "8",
          "AVAIL_DSP": "140",
          "UTIL_DSP": "5",
          "FF": "101",
          "AVAIL_FF": "96000",
          "UTIL_FF": "~0",
          "LUT": "33",
          "AVAIL_LUT": "48000",
          "UTIL_LUT": "~0",
          "BRAM_18K": "0",
          "AVAIL_BRAM": "180",
          "UTIL_BRAM": "0",
          "URAM": "0",
          "AVAIL_URAM": "0",
          "UTIL_URAM": "0"
        }
      }}
  },
  "GenerateBdFiles": "0",
  "GenData": {
    "DataVersion": "0.2",
    "Time": "2024-08-08 11:45:48 -03",
    "ToolName": "vitis_hls",
    "ToolVersion": "2023.2.2"
  }
}
